Workbook

Sheet 🗂 Mode d'emploi
B2: GRILLE D'ÉVALUATION DES ACQUIS
B3: Modèle M29 — Évaluation Bloc/Compétence/Indicateur — 4 niveaux de maîtrise — Calcul auto du taux d'atteinte — Ind. 11 (Majeure)
B6: À QUOI SERT CE DOCUMENT
C7: Cette grille est l'outil central de l'Indicateur 11 (Majeure). Elle permet de tracer pour chaque bénéficiaire le niveau d'atteinte de chaque compétence et indicateur du référentiel, sur une échelle à 4 niveaux. Le calcul automatique produit un taux d'atteinte par bloc et global qui alimente l'attestation de fin de formation (M31) et le PV de jury (M30) pour les actions certifiantes.
B9: STRUCTURE DU CLASSEUR
B10: 📚 Référentiel | C10: Saisie du référentiel de la formation : blocs de compétences, compétences, indicateurs avec leurs critères. Source unique pour les autres feuilles.
B11: 📝 Évaluation individuelle | C11: Évaluer un bénéficiaire — 1 niveau par indicateur — observations qualitatives. Calcul auto du taux par bloc et global.
B12: 📊 Synthèse multi-bénéficiaires | C12: Vue d'ensemble du groupe — taux par bénéficiaire et par bloc — détection des points faibles collectifs.
B13: 🎯 Synthèse globale | C13: Tableau de bord de la session : taux moyen global, taux de réussite, blocs à renforcer.
B15: ÉCHELLE DES NIVEAUX DE MAÎTRISE
B16: 0 — Non acquis | C16: Le bénéficiaire n'a pas atteint le niveau attendu — reprise nécessaire
B17: 1 — En cours d'acquisition | C17: Le bénéficiaire progresse mais reste partiellement compétent — consolidation requise
B18: 2 — Acquis | C18: Le bénéficiaire maîtrise la compétence dans le cadre attendu — niveau de certification atteint
B19: 3 — Maîtrisé / Expert | C19: Le bénéficiaire dépasse le niveau attendu — autonomie complète + capacité de transfert
B21: INTERPRÉTATION DES TAUX D'ATTEINTE
B22: ≥ 80% | C22: Très bon — proposition de mention pour les actions certifiantes
B23: 66% - 79% | C23: Acquis — niveau de certification atteint
B24: 50% - 65% | C24: Partiellement acquis — préconisations + bilan individuel
B25: < 50% | C25: Non acquis — non-validation — reprise ou nouvelle session
B27: 💡 Ind. 11 (Majeure) | C27: L'évaluation des acquis est une Majeure. L'audit vérifie : (1) la grille existe et est utilisée pour chaque bénéficiaire, (2) elle s'aligne avec les objectifs/référentiel publiés, (3) les seuils de validation sont définis et appliqués de manière constante. Conserver les grilles complétées 4 ans minimum (10 ans recommandés).

Sheet 📚 Référentiel
B2: 📚 RÉFÉRENTIEL DE LA FORMATION
B3: Saisie des blocs, compétences et indicateurs — source unique pour les évaluations
B6: Intitulé : | C6: [ Intitulé exact tel qu'au programme M5 ]
B7: Certif. visée : | C7: [ RNCP XXXXX / RS XXXX / Non certifiante ]
B9: Code | C9: Bloc de compétences | D9: Compétence | E9: Indicateur / Critère d'évaluation | F9: Modalité
B10: BC01-C01-I01 | C10: BC01 - Idéation projet | D10: C01 - Identifier opportunités | E10: I01 - Réalise une analyse SWOT structurée | F10: Étude de cas
B11: BC01-C01-I02 | C11: BC01 - Idéation projet | D11: C01 - Identifier opportunités | E11: I02 - Cible 3 segments potentiels argumentés | F11: Étude de cas
B12: BC01-C02-I03 | C12: BC01 - Idéation projet | D12: C02 - Construire BMC | E12: I03 - BMC complet et cohérent (9 blocs) | F12: Production écrite
B13: BC02-C03-I04 | C13: BC02 - Étude marché | D13: C03 - Analyser concurrence | E13: I04 - Veille concurrentielle ≥ 5 acteurs | F13: Production écrite
B14: BC02-C03-I05 | C14: BC02 - Étude marché | D14: C03 - Analyser concurrence | E14: I05 - Positionnement stratégique justifié | F14: Soutenance
B15: BC02-C04-I06 | C15: BC02 - Étude marché | D15: C04 - Étudier clients | E15: I06 - Réalise ≥ 5 interviews clients | F15: Mise en situation
B16: BC03-C05-I07 | C16: BC03 - Pilotage économique | D16: C05 - Construire prévi. | E16: I07 - Plan de trésorerie 12 mois cohérent | F16: Cas pratique
B17: BC03-C05-I08 | C17: BC03 - Pilotage économique | D17: C05 - Construire prévi. | E17: I08 - Justifie hypothèses commerciales | F17: Soutenance
B18: BC03-C06-I09 | C18: BC03 - Pilotage économique | D18: C06 - Suivre indicateurs | E18: I09 - Tableau de bord ≥ 5 KPI pertinents | F18: Production écrite
B19: BC04-C07-I10 | C19: BC04 - Lancement | D19: C07 - Pitcher projet | E19: I10 - Pitch 3 min — clair, structuré, convaincant | F19: Oral devant jury
B41: 💡 Astuce | C41: Le référentiel doit être strictement aligné sur la fiche RNCP/RS pour les actions certifiantes. Pour les actions non certifiantes, alignement sur les objectifs publiés dans le programme M5. Cette feuille alimente automatiquement l'évaluation individuelle.

Sheet 📝 Évaluation individuelle
B2: 📝 ÉVALUATION INDIVIDUELLE — UN BÉNÉFICIAIRE
B3: Saisir le niveau (0 à 3) pour chaque indicateur — observations qualitatives en commentaire
B6: Bénéficiaire : | C6: [ Madame / Monsieur PRÉNOM NOM ] | D6: Date évaluation : | E6: [ JJ / MM / AAAA ] | F6: Évaluateur : | G6: [ Prénom NOM ]
B8: Code | C8: Bloc | D8: Compétence | E8: Indicateur | F8: Niveau (0-3) | G8: Observations / preuve
B9: =IF('📚 Référentiel'!B10="","",'📚 Référentiel'!B10) -> BC01-C01-I01 | C9: =IF('📚 Référentiel'!C10="","",'📚 Référentiel'!C10) -> BC01 - Idéation projet | D9: =IF('📚 Référentiel'!D10="","",'📚 Référentiel'!D10) -> C01 - Identifier opportunités | E9: =IF('📚 Référentiel'!E10="","",'📚 Référentiel'!E10) -> I01 - Réalise une analyse SWOT structurée | F9: 3 | G9: Excellente SWOT — analyse fine
B10: =IF('📚 Référentiel'!B11="","",'📚 Référentiel'!B11) -> BC01-C01-I02 | C10: =IF('📚 Référentiel'!C11="","",'📚 Référentiel'!C11) -> BC01 - Idéation projet | D10: =IF('📚 Référentiel'!D11="","",'📚 Référentiel'!D11) -> C01 - Identifier opportunités | E10: =IF('📚 Référentiel'!E11="","",'📚 Référentiel'!E11) -> I02 - Cible 3 segments potentiels argumentés | F10: 2 | G10: 3 segments identifiés, justification correcte
B11: =IF('📚 Référentiel'!B12="","",'📚 Référentiel'!B12) -> BC01-C02-I03 | C11: =IF('📚 Référentiel'!C12="","",'📚 Référentiel'!C12) -> BC01 - Idéation projet | D11: =IF('📚 Référentiel'!D12="","",'📚 Référentiel'!D12) -> C02 - Construire BMC | E11: =IF('📚 Référentiel'!E12="","",'📚 Référentiel'!E12) -> I03 - BMC complet et cohérent (9 blocs) | F11: 2 | G11: BMC complet — manque cohérence ressources/coûts
B12: =IF('📚 Référentiel'!B13="","",'📚 Référentiel'!B13) -> BC02-C03-I04 | C12: =IF('📚 Référentiel'!C13="","",'📚 Référentiel'!C13) -> BC02 - Étude marché | D12: =IF('📚 Référentiel'!D13="","",'📚 Référentiel'!D13) -> C03 - Analyser concurrence | E12: =IF('📚 Référentiel'!E13="","",'📚 Référentiel'!E13) -> I04 - Veille concurrentielle ≥ 5 acteurs
B13: =IF('📚 Référentiel'!B14="","",'📚 Référentiel'!B14) -> BC02-C03-I05 | C13: =IF('📚 Référentiel'!C14="","",'📚 Référentiel'!C14) -> BC02 - Étude marché | D13: =IF('📚 Référentiel'!D14="","",'📚 Référentiel'!D14) -> C03 - Analyser concurrence | E13: =IF('📚 Référentiel'!E14="","",'📚 Référentiel'!E14) -> I05 - Positionnement stratégique justifié
B14: =IF('📚 Référentiel'!B15="","",'📚 Référentiel'!B15) -> BC02-C04-I06 | C14: =IF('📚 Référentiel'!C15="","",'📚 Référentiel'!C15) -> BC02 - Étude marché | D14: =IF('📚 Référentiel'!D15="","",'📚 Référentiel'!D15) -> C04 - Étudier clients | E14: =IF('📚 Référentiel'!E15="","",'📚 Référentiel'!E15) -> I06 - Réalise ≥ 5 interviews clients
B15: =IF('📚 Référentiel'!B16="","",'📚 Référentiel'!B16) -> BC03-C05-I07 | C15: =IF('📚 Référentiel'!C16="","",'📚 Référentiel'!C16) -> BC03 - Pilotage économique | D15: =IF('📚 Référentiel'!D16="","",'📚 Référentiel'!D16) -> C05 - Construire prévi. | E15: =IF('📚 Référentiel'!E16="","",'📚 Référentiel'!E16) -> I07 - Plan de trésorerie 12 mois cohérent
B16: =IF('📚 Référentiel'!B17="","",'📚 Référentiel'!B17) -> BC03-C05-I08 | C16: =IF('📚 Référentiel'!C17="","",'📚 Référentiel'!C17) -> BC03 - Pilotage économique | D16: =IF('📚 Référentiel'!D17="","",'📚 Référentiel'!D17) -> C05 - Construire prévi. | E16: =IF('📚 Référentiel'!E17="","",'📚 Référentiel'!E17) -> I08 - Justifie hypothèses commerciales
B17: =IF('📚 Référentiel'!B18="","",'📚 Référentiel'!B18) -> BC03-C06-I09 | C17: =IF('📚 Référentiel'!C18="","",'📚 Référentiel'!C18) -> BC03 - Pilotage économique | D17: =IF('📚 Référentiel'!D18="","",'📚 Référentiel'!D18) -> C06 - Suivre indicateurs | E17: =IF('📚 Référentiel'!E18="","",'📚 Référentiel'!E18) -> I09 - Tableau de bord ≥ 5 KPI pertinents
B18: =IF('📚 Référentiel'!B19="","",'📚 Référentiel'!B19) -> BC04-C07-I10 | C18: =IF('📚 Référentiel'!C19="","",'📚 Référentiel'!C19) -> BC04 - Lancement | D18: =IF('📚 Référentiel'!D19="","",'📚 Référentiel'!D19) -> C07 - Pitcher projet | E18: =IF('📚 Référentiel'!E19="","",'📚 Référentiel'!E19) -> I10 - Pitch 3 min — clair, structuré, convaincant
B19: =IF('📚 Référentiel'!B20="","",'📚 Référentiel'!B20) | C19: =IF('📚 Référentiel'!C20="","",'📚 Référentiel'!C20) | D19: =IF('📚 Référentiel'!D20="","",'📚 Référentiel'!D20) | E19: =IF('📚 Référentiel'!E20="","",'📚 Référentiel'!E20)
B20: =IF('📚 Référentiel'!B21="","",'📚 Référentiel'!B21) | C20: =IF('📚 Référentiel'!C21="","",'📚 Référentiel'!C21) | D20: =IF('📚 Référentiel'!D21="","",'📚 Référentiel'!D21) | E20: =IF('📚 Référentiel'!E21="","",'📚 Référentiel'!E21)
B21: =IF('📚 Référentiel'!B22="","",'📚 Référentiel'!B22) | C21: =IF('📚 Référentiel'!C22="","",'📚 Référentiel'!C22) | D21: =IF('📚 Référentiel'!D22="","",'📚 Référentiel'!D22) | E21: =IF('📚 Référentiel'!E22="","",'📚 Référentiel'!E22)
B22: =IF('📚 Référentiel'!B23="","",'📚 Référentiel'!B23) | C22: =IF('📚 Référentiel'!C23="","",'📚 Référentiel'!C23) | D22: =IF('📚 Référentiel'!D23="","",'📚 Référentiel'!D23) | E22: =IF('📚 Référentiel'!E23="","",'📚 Référentiel'!E23)
B23: =IF('📚 Référentiel'!B24="","",'📚 Référentiel'!B24) | C23: =IF('📚 Référentiel'!C24="","",'📚 Référentiel'!C24) | D23: =IF('📚 Référentiel'!D24="","",'📚 Référentiel'!D24) | E23: =IF('📚 Référentiel'!E24="","",'📚 Référentiel'!E24)
... B38: =IF('📚 Référentiel'!B39="","",'📚 Référentiel'!B39) | C38: =IF('📚 Référentiel'!C39="","",'📚 Référentiel'!C39) | D38: =IF('📚 Référentiel'!D39="","",'📚 Référentiel'!D39) | E38: =IF('📚 Référentiel'!E39="","",'📚 Référentiel'!E39)
B40: SYNTHÈSE PAR BLOC DE COMPÉTENCES
B41: Bloc | C41: Nb indicateurs | D41: Nb évalués | E41: Score moyen / 3 | F41: Taux d'atteinte | G41: Niveau global
B42: BC01 - Idéation projet | C42: =IF(B42="","",COUNTIF(C9:C38,B42)) -> 3 | D42: =IF(B42="","",COUNTIFS(C9:C38,B42,F9:F38,"<>")) -> 3 | E42: =IFERROR(IF(B42="","",AVERAGEIFS(F9:F38,C9:C38,B42)),"") -> 2.3333333 | F42: =IF(E42="","",E42/3) -> 0.77777778 | G42: =IF(F42="","",IF(F42>=0.8,"✨ Maîtrisé",IF(F42>=0.66,"✓ Acquis",IF(F42>=0.5,"⚠ Partiel","❌ Non acquis")))) -> ✓ Acquis
B43: BC02 - Étude marché | C43: =IF(B43="","",COUNTIF(C9:C38,B43)) -> 3 | D43: =IF(B43="","",COUNTIFS(C9:C38,B43,F9:F38,"<>")) -> 0 | E43: =IFERROR(IF(B43="","",AVERAGEIFS(F9:F38,C9:C38,B43)),"") | F43: =IF(E43="","",E43/3) | G43: =IF(F43="","",IF(F43>=0.8,"✨ Maîtrisé",IF(F43>=0.66,"✓ Acquis",IF(F43>=0.5,"⚠ Partiel","❌ Non acquis"))))
B44: BC03 - Pilotage économique | C44: =IF(B44="","",COUNTIF(C9:C38,B44)) -> 3 | D44: =IF(B44="","",COUNTIFS(C9:C38,B44,F9:F38,"<>")) -> 0 | E44: =IFERROR(IF(B44="","",AVERAGEIFS(F9:F38,C9:C38,B44)),"") | F44: =IF(E44="","",E44/3) | G44: =IF(F44="","",IF(F44>=0.8,"✨ Maîtrisé",IF(F44>=0.66,"✓ Acquis",IF(F44>=0.5,"⚠ Partiel","❌ Non acquis"))))
B45: BC04 - Lancement | C45: =IF(B45="","",COUNTIF(C9:C38,B45)) -> 1 | D45: =IF(B45="","",COUNTIFS(C9:C38,B45,F9:F38,"<>")) -> 0 | E45: =IFERROR(IF(B45="","",AVERAGEIFS(F9:F38,C9:C38,B45)),"") | F45: =IF(E45="","",E45/3) | G45: =IF(F45="","",IF(F45>=0.8,"✨ Maîtrisé",IF(F45>=0.66,"✓ Acquis",IF(F45>=0.5,"⚠ Partiel","❌ Non acquis"))))
C46: =IF(B46="","",COUNTIF(C9:C38,B46)) | D46: =IF(B46="","",COUNTIFS(C9:C38,B46,F9:F38,"<>")) | E46: =IFERROR(IF(B46="","",AVERAGEIFS(F9:F38,C9:C38,B46)),"") | F46: =IF(E46="","",E46/3) | G46: =IF(F46="","",IF(F46>=0.8,"✨ Maîtrisé",IF(F46>=0.66,"✓ Acquis",IF(F46>=0.5,"⚠ Partiel","❌ Non acquis"))))
B48: TOTAL — TAUX D'ATTEINTE GLOBAL | E48: =IFERROR(AVERAGE(F9:F38),"") -> 2.3333333 | F48: =IF(E48="","",E48/3) -> 0.77777778 | G48: =IF(F48="","",IF(F48>=0.8,"✨ Mention",IF(F48>=0.66,"✓ ADMIS",IF(F48>=0.5,"⚠ Partiel","❌ AJOURNÉ")))) -> ✓ ADMIS
B50: BILAN QUALITATIF & PRÉCONISATIONS
B51: Compétences acquises (points forts) | D51: [ Lister les compétences validées au niveau 2 ou 3 ]
B52: Compétences en cours / à consolider | D52: [ Lister les compétences au niveau 1 et préconisations ]
B53: Compétences non acquises | D53: [ Lister les compétences au niveau 0 et plan d'action ]
B54: Préconisations post-formation | D54: [ Coaching · module complémentaire · ressources · etc. ]

Sheet 📊 Synthèse multi-bénéf
B2: 📊 SYNTHÈSE PAR BÉNÉFICIAIRE — VUE D'ENSEMBLE
B3: Tableau de bord du groupe — taux par bénéficiaire et par bloc — détection des blocs collectivement faibles
B6: 📋 Cette feuille s'utilise en consolidation après que chaque évaluation individuelle a été saisie sur une copie distincte du fichier (un fichier par bénéficiaire) puis recopiée ici manuellement ou par lien.
B8: N° | C8: Bénéficiaire | D8: BC01 | E8: BC02 | F8: BC03 | G8: BC04 | H8: BC05 | I8: Taux global | J8: Décision
B9: 01 | C9: Marie DUPONT | D9: 0.78 | E9: 0.83 | F9: 0.72 | G9: 0.92 | I9: =IFERROR(AVERAGE(D9:H9),"") -> 0.8125 | J9: =IF(I9="","",IF(I9>=0.8,"✨ Mention",IF(I9>=0.66,"✓ ADMIS",IF(I9>=0.5,"⚠ Partiel","❌ AJOURNÉ")))) -> ✨ Mention
B10: 02 | C10: Karim MARTIN | D10: 0.92 | E10: 0.85 | F10: 0.78 | G10: 0.83 | I10: =IFERROR(AVERAGE(D10:H10),"") -> 0.845 | J10: =IF(I10="","",IF(I10>=0.8,"✨ Mention",IF(I10>=0.66,"✓ ADMIS",IF(I10>=0.5,"⚠ Partiel","❌ AJOURNÉ")))) -> ✨ Mention
B11: 03 | C11: Sophie BERNARD | D11: 0.55 | E11: 0.61 | F11: 0.5 | G11: 0.67 | I11: =IFERROR(AVERAGE(D11:H11),"") -> 0.5825 | J11: =IF(I11="","",IF(I11>=0.8,"✨ Mention",IF(I11>=0.66,"✓ ADMIS",IF(I11>=0.5,"⚠ Partiel","❌ AJOURNÉ")))) -> ⚠ Partiel
B12: 04 | C12: Thomas LEROY | D12: 0.33 | E12: 0.42 | F12: 0.25 | G12: 0.5 | I12: =IFERROR(AVERAGE(D12:H12),"") -> 0.375 | J12: =IF(I12="","",IF(I12>=0.8,"✨ Mention",IF(I12>=0.66,"✓ ADMIS",IF(I12>=0.5,"⚠ Partiel","❌ AJOURNÉ")))) -> ❌ AJOURNÉ
I13: =IFERROR(AVERAGE(D13:H13),"") | J13: =IF(I13="","",IF(I13>=0.8,"✨ Mention",IF(I13>=0.66,"✓ ADMIS",IF(I13>=0.5,"⚠ Partiel","❌ AJOURNÉ"))))
I14: =IFERROR(AVERAGE(D14:H14),"") | J14: =IF(I14="","",IF(I14>=0.8,"✨ Mention",IF(I14>=0.66,"✓ ADMIS",IF(I14>=0.5,"⚠ Partiel","❌ AJOURNÉ"))))
I15: =IFERROR(AVERAGE(D15:H15),"") | J15: =IF(I15="","",IF(I15>=0.8,"✨ Mention",IF(I15>=0.66,"✓ ADMIS",IF(I15>=0.5,"⚠ Partiel","❌ AJOURNÉ"))))
I16: =IFERROR(AVERAGE(D16:H16),"") | J16: =IF(I16="","",IF(I16>=0.8,"✨ Mention",IF(I16>=0.66,"✓ ADMIS",IF(I16>=0.5,"⚠ Partiel","❌ AJOURNÉ"))))
I17: =IFERROR(AVERAGE(D17:H17),"") | J17: =IF(I17="","",IF(I17>=0.8,"✨ Mention",IF(I17>=0.66,"✓ ADMIS",IF(I17>=0.5,"⚠ Partiel","❌ AJOURNÉ"))))
I18: =IFERROR(AVERAGE(D18:H18),"") | J18: =IF(I18="","",IF(I18>=0.8,"✨ Mention",IF(I18>=0.66,"✓ ADMIS",IF(I18>=0.5,"⚠ Partiel","❌ AJOURNÉ"))))
I19: =IFERROR(AVERAGE(D19:H19),"") | J19: =IF(I19="","",IF(I19>=0.8,"✨ Mention",IF(I19>=0.66,"✓ ADMIS",IF(I19>=0.5,"⚠ Partiel","❌ AJOURNÉ"))))
I20: =IFERROR(AVERAGE(D20:H20),"") | J20: =IF(I20="","",IF(I20>=0.8,"✨ Mention",IF(I20>=0.66,"✓ ADMIS",IF(I20>=0.5,"⚠ Partiel","❌ AJOURNÉ"))))
I21: =IFERROR(AVERAGE(D21:H21),"") | J21: =IF(I21="","",IF(I21>=0.8,"✨ Mention",IF(I21>=0.66,"✓ ADMIS",IF(I21>=0.5,"⚠ Partiel","❌ AJOURNÉ"))))
I22: =IFERROR(AVERAGE(D22:H22),"") | J22: =IF(I22="","",IF(I22>=0.8,"✨ Mention",IF(I22>=0.66,"✓ ADMIS",IF(I22>=0.5,"⚠ Partiel","❌ AJOURNÉ"))))
I23: =IFERROR(AVERAGE(D23:H23),"") | J23: =IF(I23="","",IF(I23>=0.8,"✨ Mention",IF(I23>=0.66,"✓ ADMIS",IF(I23>=0.5,"⚠ Partiel","❌ AJOURNÉ"))))
I24: =IFERROR(AVERAGE(D24:H24),"") | J24: =IF(I24="","",IF(I24>=0.8,"✨ Mention",IF(I24>=0.66,"✓ ADMIS",IF(I24>=0.5,"⚠ Partiel","❌ AJOURNÉ"))))
... I28: =IFERROR(AVERAGE(D28:H28),"") | J28: =IF(I28="","",IF(I28>=0.8,"✨ Mention",IF(I28>=0.66,"✓ ADMIS",IF(I28>=0.5,"⚠ Partiel","❌ AJOURNÉ"))))
B30: MOYENNE | D30: =IFERROR(AVERAGE(D9:D28),"") -> 0.645 | E30: =IFERROR(AVERAGE(E9:E28),"") -> 0.6775 | F30: =IFERROR(AVERAGE(F9:F28),"") -> 0.5625 | G30: =IFERROR(AVERAGE(G9:G28),"") -> 0.73 | H30: =IFERROR(AVERAGE(H9:H28),"") | I30: =IFERROR(AVERAGE(I9:I28),"") -> 0.65375
B32: 🎯 INDICATEURS DE PILOTAGE
B33: Bénéficiaires évalués | F33: =COUNTA(C9:C28) -> 4
B34: Taux de réussite (Admis + Mention) | F34: =IFERROR((COUNTIF(J9:J28,"✓ ADMIS")+COUNTIF(J9:J28,"✨ Mention"))/COUNTA(C9:C28),0) -> 0.5
B35: Bloc le plus faible (moyenne la plus basse) | F35: =IFERROR(INDEX($D$8:$H$8,MATCH(MIN(D30:H30),D30:H30,0))&" ("&TEXT(MIN(D30:H30),"0%")&")","") -> BC03 (56%)
